traffic_light_fsm.v
module traffic_light_fsm (
    input clk,
    input rst,
    output reg [2:0] light  // [Red Yellow Green]
);

    // State encoding using localparams
    localparam RED    = 2'b00;
    localparam GREEN  = 2'b01;
    localparam YELLOW = 2'b10;

    reg [1:0] state, next_state;
    reg [3:0] counter;

    // State register and counter
    always @(posedge clk) begin
        if (rst) begin
            state <= RED;
            counter <= 0;
        end else begin
            state <= next_state;

            if (counter == 0) begin
                if (state == RED) counter <= 5;
                else if (state == GREEN) counter <= 5;
                else if (state == YELLOW) counter <= 2;
            end else begin
                counter <= counter - 1;
            end
        end
    end

    // Next state logic
    always @(*) begin
        case (state)
            RED:    next_state = (counter == 0) ? GREEN : RED;
            GREEN:  next_state = (counter == 0) ? YELLOW : GREEN;
            YELLOW: next_state = (counter == 0) ? RED : YELLOW;
            default: next_state = RED;
        endcase
    end

    // Output logic
    always @(*) begin
        case (state)
            RED:    light = 3'b100;  // Red ON
            GREEN:  light = 3'b001;  // Green ON
            YELLOW: light = 3'b010;  // Yellow ON
            default: light = 3'b000;
        endcase
    end

endmodule

traffic_light_fsm_tb.v
`timescale 1ns / 1ps

module traffic_light_fsm_tb;

    reg clk;
    reg rst;
    wire [2:0] light;

    // Instantiate the FSM
    traffic_light_fsm uut (
        .clk(clk),
        .rst(rst),
        .light(light)
    );

    // Clock generation: 10ns period (100MHz)
    initial begin
        clk = 0;
        forever #5 clk = ~clk;
    end

    // Stimulus
    initial begin
        // Dump VCD waveform
        $dumpfile("traffic_light_fsm.vcd");
        $dumpvars(0, traffic_light_fsm_tb);

        // Apply reset
        rst = 1;
        #10;
        rst = 0;

        // Run long enough to observe several cycles
        #200;

        $finish;
    end

    // Monitor state transitions
    initial begin
        $display("Time\tclk\trst\tlight");
        $monitor("%g\t%b\t%b\t%b", $time, clk, rst, light);
    end

endmodule

traffic_light_fsm.vcd
$date
	Sun Jun 29 09:22:53 2025
$end
$version
	Icarus Verilog
$end
$timescale
	1ps
$end
$scope module traffic_light_fsm_tb $end
$var wire 3 ! light [2:0] $end
$var reg 1 " clk $end
$var reg 1 # rst $end
$scope module uut $end
$var wire 1 " clk $end
$var wire 1 # rst $end
$var parameter 2 $ GREEN $end
$var parameter 2 % RED $end
$var parameter 2 & YELLOW $end
$var reg 4 ' counter [3:0] $end
$var reg 3 ( light [2:0] $end
$var reg 2 ) next_state [1:0] $end
$var reg 2 * state [1:0] $end
$upscope $end
$upscope $end
$enddefinitions $end
$comment Show the parameter values. $end
$dumpall
b10 &
b0 %
b1 $
$end
#0
$dumpvars
bx *
bx )
bx (
bx '
1#
0"
bx !
$end
#5000
b100 !
b100 (
b1 )
b0 '
b0 *
1"
#10000
0"
0#
#15000
b1 !
b1 (
b101 '
b1 *
1"
#20000
0"
#25000
b100 '
1"
#30000
0"
#35000
b11 '
1"
#40000
0"
#45000
b10 '
1"
#50000
0"
#55000
b1 '
1"
#60000
0"
#65000
b10 )
b0 '
1"
#70000
0"
#75000
b10 !
b10 (
b101 '
b10 *
1"
#80000
0"
#85000
b100 '
1"
#90000
0"
#95000
b11 '
1"
#100000
0"
#105000
b10 '
1"
#110000
0"
#115000
b1 '
1"
#120000
0"
#125000
b0 )
b0 '
1"
#130000
0"
#135000
b100 !
b100 (
b10 '
b0 *
1"
#140000
0"
#145000
b1 '
1"
#150000
0"
#155000
b1 )
b0 '
1"
#160000
0"
#165000
b1 !
b1 (
b101 '
b1 *
1"
#170000
0"
#175000
b100 '
1"
#180000
0"
#185000
b11 '
1"
#190000
0"
#195000
b10 '
1"
#200000
0"
#205000
b1 '
1"
